{
  "lssdConfig": {
    "host": "",
    "port": 50051
  },
  "xsnLNDConfig": {
    "certPath":"certs/lnd_xsn.cert",
    "host": "localhost",
    "port": 10003
  },
  "ltcLNDConfig": {
    "certPath":"certs/lnd_ltc.cert",
    "host": "localhost",
    "port": 10001
  },
  "btcLNDConfig": {
    "certPath":"certs/lnd_btc.cert",
    "host": "localhost",
    "port": 10009
  },
  "orders": [{
    "side": "sell",
    "tradingPair": "XSN_LTC",
    "priceRangeStart": 95000,
    "priceRangeEnd": 95005,
    "priceRangeStepSize": 1,
    "fixedFunding": 100000
  }]
}
